[
  {
    "localid": 9991,
    "text": "test-1",
    "importance": 0,
    "done": true,
    "created": 0,
    "deadline": "",
    "changed": 0,
    "deletepending": false
  },
  {
    "localid": 9992,
    "text": "test-2",
    "importance": 1,
    "done": true,
    "created": 0,
    "deadline": "",
    "changed": 0,
    "deletepending": false
  },
  {
    "localid": 9993,
    "text": "test-3",
    "importance": 2,
    "done": true,
    "created": 0,
    "deadline": "",
    "changed": 0,
    "deletepending": false
  },
  {
    "localid": 9994,
    "text": "test-1",
    "importance": 0,
    "done": false,
    "created": 0,
    "deadline": "",
    "changed": 0,
    "deletepending": false
  },
  {
    "localid": 9995,
    "text": "test-2",
    "importance": 1,
    "done": false,
    "created": 0,
    "deadline": "",
    "changed": 0,
    "deletepending": false
  },
  {
    "localid": 9996,
    "text": "test-3",
    "importance": 2,
    "done": false,
    "created": 0,
    "deadline": "",
    "changed": 0,
    "deletepending": false
  }
]